meraki_client/__init__.py
meraki_client/_common.py
meraki_client/_session.py
meraki_client/exceptions.py
meraki_client/py.typed
meraki_client/_api/__init__.py
meraki_client/_api/administered.py
meraki_client/_api/appliance.py
meraki_client/_api/camera.py
meraki_client/_api/campus_gateway.py
meraki_client/_api/cellular_gateway.py
meraki_client/_api/devices.py
meraki_client/_api/insight.py
meraki_client/_api/licensing.py
meraki_client/_api/nac.py
meraki_client/_api/networks.py
meraki_client/_api/organizations.py
meraki_client/_api/sensor.py
meraki_client/_api/sm.py
meraki_client/_api/spaces.py
meraki_client/_api/switch.py
meraki_client/_api/wireless.py
meraki_client/_api/wireless_controller.py
meraki_client/_api/batch/__init__.py
meraki_client/_api/batch/appliance.py
meraki_client/_api/batch/camera.py
meraki_client/_api/batch/campus_gateway.py
meraki_client/_api/batch/cellular_gateway.py
meraki_client/_api/batch/devices.py
meraki_client/_api/batch/insight.py
meraki_client/_api/batch/nac.py
meraki_client/_api/batch/networks.py
meraki_client/_api/batch/organizations.py
meraki_client/_api/batch/sensor.py
meraki_client/_api/batch/sm.py
meraki_client/_api/batch/spaces.py
meraki_client/_api/batch/switch.py
meraki_client/_api/batch/wireless.py
meraki_client/aio/__init__.py
meraki_client/aio/_session.py
meraki_client/aio/_api/__init__.py
meraki_client/aio/_api/administered.py
meraki_client/aio/_api/appliance.py
meraki_client/aio/_api/camera.py
meraki_client/aio/_api/campus_gateway.py
meraki_client/aio/_api/cellular_gateway.py
meraki_client/aio/_api/devices.py
meraki_client/aio/_api/insight.py
meraki_client/aio/_api/licensing.py
meraki_client/aio/_api/nac.py
meraki_client/aio/_api/networks.py
meraki_client/aio/_api/organizations.py
meraki_client/aio/_api/sensor.py
meraki_client/aio/_api/sm.py
meraki_client/aio/_api/spaces.py
meraki_client/aio/_api/switch.py
meraki_client/aio/_api/wireless.py
meraki_client/aio/_api/wireless_controller.py
meraki_client/schemas/__init__.py
meraki_client-0.5.0.dist-info/METADATA
meraki_client-0.5.0.dist-info/WHEEL
meraki_client-0.5.0.dist-info/licenses/LICENSE
meraki_client-0.5.0.dist-info/RECORD
