Metadata-Version: 2.4
Name: meraki-client
Version: 0.5.0
Summary: Python client for Meraki Dashboard API
Project-URL: homepage, https://meraki-client.readthedocs.io
Project-URL: repository, https://github.com/ollipa/meraki-client-python
Author-email: Olli Paakkunainen <olli@paakkunainen.fi>
License-Expression: MIT
License-File: LICENSE
Keywords: cisco,dashboard,meraki
Classifier: Programming Language :: Python :: 3
Classifier: Programming Language :: Python :: 3 :: Only
Classifier: Programming Language :: Python :: 3.11
Classifier: Programming Language :: Python :: 3.12
Classifier: Programming Language :: Python :: 3.13
Classifier: Programming Language :: Python :: 3.14
Classifier: Programming Language :: Python :: 3.15
Classifier: Typing :: Typed
Requires-Python: >=3.11
Requires-Dist: httpx<0.29.0,>=0.28.1
Requires-Dist: pydantic<3.0.0,>=2.12.5
